tests/__init__.py
tests/aws_base.py
tests/test_aws_api_gateway.py
tests/test_aws_internet_gateway.py
tests/test_aws_lambda.py
tests/test_aws_network_acl.py
tests/test_aws_s3_bucket.py
tests/test_tools.py
utils2devops/__init__.py
utils2devops/aws/__init__.py
utils2devops/aws/api_gateway_v2.py
utils2devops/aws/aws_lambda.py
utils2devops/aws/internet_gateway.py
utils2devops/aws/lambda_ssm.py
utils2devops/aws/network_acl.py
utils2devops/aws/route_table.py
utils2devops/aws/s3_bucket.py
utils2devops/aws/secretmanager.py
utils2devops/aws/security_group.py
utils2devops/aws/ssm.py
utils2devops/aws/subnet.py
utils2devops/aws/vpc.py
utils2devops/lxd_lxc/__init__.py
utils2devops/lxd_lxc/base.py
utils2devops/lxd_lxc/container.py
utils2devops/lxd_lxc/image.py
utils2devops/lxd_lxc/lxc_container.py
utils2devops/lxd_lxc/lxc_delete.py
utils2devops/lxd_lxc/lxc_juju_controller.py
utils2devops/lxd_lxc/network.py
utils2devops/lxd_lxc/profile.py
utils2devops/lxd_lxc/storage.py
utils2devops/tools/__init__.py
utils2devops/tools/description.py
utils2devops/tools/file.py
utils2devops/tools/single_sourcing_package_version.py
utils2devops/tools/string.py
utils2devops-0.7.0.dist-info/licenses/LICENSE
utils2devops-0.7.0.dist-info/METADATA
utils2devops-0.7.0.dist-info/WHEEL
utils2devops-0.7.0.dist-info/top_level.txt
utils2devops-0.7.0.dist-info/RECORD
