Metadata-Version: 2.4
Name: utils2devops
Version: 0.7.0
Summary: python 3 functions and class that can be helpful in the all working day
Home-page: http://github.com/alainivars/utils2devops
Author: Alain IVARS
Author-email: Alain Ivars <alainivars@gmail.com>
License:                                  Apache License
Keywords: Devops Docker Kubernetes Terraform Lxd Lxc Aws
Classifier: Development Status :: 3 - Alpha
Classifier: Intended Audience :: Developers
Classifier: Intended Audience :: System Administrators
Classifier: Operating System :: OS Independent
Classifier: License :: OSI Approved :: Apache Software License
Classifier: Programming Language :: Python
Classifier: Programming Language :: Python :: 3
Classifier: Programming Language :: Python :: 3.10
Classifier: Programming Language :: Python :: 3.12
Requires-Python: >=3.10
License-File: LICENSE
Requires-Dist: deprecation
Requires-Dist: pylxd
Requires-Dist: docker
Requires-Dist: boto3
Requires-Dist: botocore
Requires-Dist: s3transfer
Requires-Dist: ansible
Requires-Dist: proxmoxer
Requires-Dist: python-dateutil
Requires-Dist: tox
Requires-Dist: pytest
Requires-Dist: molecule
Requires-Dist: testinfra
Requires-Dist: pycodestyle
Requires-Dist: pytest-cov
Requires-Dist: coverage
Requires-Dist: Sphinx
Requires-Dist: readthedocs-sphinx-ext
Requires-Dist: requests
Requires-Dist: cookiecutter
Requires-Dist: urllib3
Requires-Dist: pygments
Requires-Dist: twine>=6.1.0
Requires-Dist: setuptools>=80.7.1
Dynamic: author
Dynamic: home-page
Dynamic: license-file
Dynamic: requires-python
